clu/__init__.py
clu/__main__.py
clu/actor.py
clu/base.py
clu/client.py
clu/command.py
clu/device.py
clu/exceptions.py
clu/model.py
clu/protocol.py
clu/store.py
clu/testing.py
clu/tools.py
clu/websocket.py
clu/legacy/__init__.py
clu/legacy/actor.py
clu/legacy/tron.py
clu/legacy/types/__init__.py
clu/legacy/types/html.py
clu/legacy/types/keys.py
clu/legacy/types/messages.py
clu/legacy/types/parser.py
clu/legacy/types/pvt.py
clu/legacy/types/types.py
clu/legacy/types/ply/__init__.py
clu/legacy/types/ply/cpp.py
clu/legacy/types/ply/ctokens.py
clu/legacy/types/ply/lex.py
clu/legacy/types/ply/yacc.py
clu/legacy/types/ply/ygen.py
clu/parsers/__init__.py
clu/parsers/click.py
clu/parsers/json.py
sdss_clu-2.6.0.dist-info/METADATA
sdss_clu-2.6.0.dist-info/WHEEL
sdss_clu-2.6.0.dist-info/entry_points.txt
sdss_clu-2.6.0.dist-info/licenses/LICENSE.md
sdss_clu-2.6.0.dist-info/RECORD
