Metadata-Version: 2.4
Name: sdss-clu
Version: 2.6.0
Summary: A new protocol for SDSS actors.
Project-URL: Homepage, https://github.com/sdss/clu
Project-URL: Repository, https://github.com/sdss/clu
Project-URL: Documentation, https://clu.readthedocs.io/en/latest/
Author-email: José Sánchez-Gallego <gallegoj@uw.edu>
License: BSD-3-Clause
License-File: LICENSE.md
Requires-Python: <4.0,>=3.9
Requires-Dist: aio-pika>=9.0.0
Requires-Dist: aiormq>=6.6.4
Requires-Dist: click-aliases>=1.0.4
Requires-Dist: click-default-group>=1.2.2
Requires-Dist: click>=8.0
Requires-Dist: jsonschema>=4.0.1
Requires-Dist: prompt-toolkit>=3.0.6
Requires-Dist: pydantic>=2.10.2
Requires-Dist: sdsstools>=1.9.1
Requires-Dist: unclick>=0.1.0b5
Provides-Extra: websockets
Requires-Dist: websockets>=11.0.3; extra == 'websockets'
